camote
