Metadata-Version: 1.0
Name: camote-queue
Version: 0.1.15
Summary: Redis based queue that supports fetching job position.
Home-page: https://github.com/marconi/camote-queue
Author: Marconi Moreto
Author-email: caketoad@gmail.com
License: Copyright (c) 2012 Marconi Moreto.
